suli_mcp_self_study/__init__.py
suli_mcp_self_study-0.1.0.dist-info/WHEEL
suli_mcp_self_study-0.1.0.dist-info/entry_points.txt
suli_mcp_self_study-0.1.0.dist-info/METADATA
suli_mcp_self_study-0.1.0.dist-info/RECORD
