Metadata-Version: 2.3
Name: suli-mcp-self-study
Version: 0.1.0
Summary: Add your description here
Author: xuanyun-su
Author-email: xuanyun-su <suli249221@163.com>
Requires-Dist: mcp[cli]>=1.13.1
Requires-Python: >=3.13
